mlektic/__init__.py
mlektic/linear_reg/__init__.py
mlektic/linear_reg/linear_regression_archt.py
mlektic/linear_reg/linear_regression_tf.py
mlektic/linear_reg/linear_regression_torch.py
mlektic/linear_reg/linreg_utils.py
mlektic/linear_reg/linreg_utils_torch.py
mlektic/logistic_reg/__init__.py
mlektic/logistic_reg/logistic_regression_archt.py
mlektic/logistic_reg/logistic_regression_tf.py
mlektic/logistic_reg/logistic_regression_torch.py
mlektic/logistic_reg/logreg_utils.py
mlektic/logistic_reg/metrics_binary.py
mlektic/methods/__init__.py
mlektic/methods/linreg_trainers_torch.py
mlektic/methods/logreg_trainers_torch.py
mlektic/methods/optimizer_archt.py
mlektic/methods/regularizer_archt.py
mlektic/methods/trainers.py
mlektic/methods/base/__init__.py
mlektic/methods/base/regularizers.py
mlektic/plot_utils/__init__.py
mlektic/plot_utils/plot_utils.py
mlektic/preprocessing/__init__.py
mlektic/preprocessing/dataframes_utils.py
mlektic/reporting/__init__.py
mlektic/reporting/collector.py
mlektic/reporting/renderer.py
mlektic/reporting/utils.py
mlektic/reporting/templates/report_template_en.html
mlektic/reporting/templates/report_template_es.html
mlektic-1.0.8.dist-info/licenses/LICENSE
mlektic-1.0.8.dist-info/METADATA
mlektic-1.0.8.dist-info/WHEEL
mlektic-1.0.8.dist-info/top_level.txt
mlektic-1.0.8.dist-info/RECORD
