Metadata-Version: 2.4
Name: mlektic
Version: 1.0.8
Summary: A Python ML library to use and visualize gradient descent for linear and logistic regression optimization.
Author-email: Daniel Antonio García Escobar <contacto@dialektico.com>
Project-URL: Source, https://github.com/DanielDialektico/mlektic
Project-URL: Documentation, https://dialektico.com/mlektic/docs/
Classifier: Programming Language :: Python :: 3.11
Classifier: License :: OSI Approved :: Apache Software License
Classifier: Operating System :: OS Independent
Requires-Python: <3.13,>=3.8
License-File: LICENSE
Requires-Dist: numpy<3.0,>=2.0
Requires-Dist: pandas<2.3,>=2.0
Requires-Dist: polars<1.29,>=1.25
Requires-Dist: scikit-learn<1.7,>=1.2
Requires-Dist: matplotlib<3.11,>=3.8
Requires-Dist: torch==2.6.*
Requires-Dist: psutil>=5.9
Provides-Extra: tensorflow
Requires-Dist: tensorflow<2.19,>=2.18; extra == "tensorflow"
Provides-Extra: dev
Requires-Dist: pytest>=7.4.0; extra == "dev"
Requires-Dist: setuptools>=72.1.0; extra == "dev"
Dynamic: license-file
